Products.MimetypesRegistry-3.0.1-py3.11-nspkg.pth
Products/MimetypesRegistry/MimeTypeItem.py
Products/MimetypesRegistry/MimeTypesRegistry.py
Products/MimetypesRegistry/__init__.py
Products/MimetypesRegistry/common.py
Products/MimetypesRegistry/configure.zcml
Products/MimetypesRegistry/encoding.py
Products/MimetypesRegistry/interfaces.py
Products/MimetypesRegistry/setuphandlers.py
Products/MimetypesRegistry/testing.py
Products/MimetypesRegistry/tool.gif
Products/MimetypesRegistry/icons/application.png
Products/MimetypesRegistry/icons/audio.png
Products/MimetypesRegistry/icons/avi.png
Products/MimetypesRegistry/icons/c.png
Products/MimetypesRegistry/icons/core.png
Products/MimetypesRegistry/icons/cpp.png
Products/MimetypesRegistry/icons/deb.png
Products/MimetypesRegistry/icons/doc.png
Products/MimetypesRegistry/icons/docx.png
Products/MimetypesRegistry/icons/down.png
Products/MimetypesRegistry/icons/dvi.png
Products/MimetypesRegistry/icons/exe.png
Products/MimetypesRegistry/icons/f.png
Products/MimetypesRegistry/icons/font.png
Products/MimetypesRegistry/icons/gf.png
Products/MimetypesRegistry/icons/h.png
Products/MimetypesRegistry/icons/html.png
Products/MimetypesRegistry/icons/image.png
Products/MimetypesRegistry/icons/info.png
Products/MimetypesRegistry/icons/iso.png
Products/MimetypesRegistry/icons/java.png
Products/MimetypesRegistry/icons/log.png
Products/MimetypesRegistry/icons/man.png
Products/MimetypesRegistry/icons/message.png
Products/MimetypesRegistry/icons/midi.png
Products/MimetypesRegistry/icons/mime.png
Products/MimetypesRegistry/icons/o.png
Products/MimetypesRegistry/icons/pdf.png
Products/MimetypesRegistry/icons/pk.png
Products/MimetypesRegistry/icons/pl.png
Products/MimetypesRegistry/icons/png.png
Products/MimetypesRegistry/icons/ppt.png
Products/MimetypesRegistry/icons/pptx.png
Products/MimetypesRegistry/icons/ps.png
Products/MimetypesRegistry/icons/py.png
Products/MimetypesRegistry/icons/quicktime.png
Products/MimetypesRegistry/icons/rar.png
Products.MimetypesRegistry-3.0.1.dist-info/METADATA
Products.MimetypesRegistry-3.0.1.dist-info/WHEEL
Products.MimetypesRegistry-3.0.1.dist-info/namespace_packages.txt
Products.MimetypesRegistry-3.0.1.dist-info/top_level.txt
Products.MimetypesRegistry-3.0.1.dist-info/RECORD
