Metadata-Version: 2.1
Name: Products.MimetypesRegistry
Version: 3.0.1
Summary: MIME type handling for Zope
Home-page: https://pypi.org/project/Products.MimetypesRegistry
Author: Benjamin Saller
Author-email: plone-developers@lists.sourceforge.net
License: GPL
Keywords: Zope mimetype registry
Classifier: Development Status :: 5 - Production/Stable
Classifier: Framework :: Zope :: 5
Classifier: Operating System :: OS Independent
Classifier: Framework :: Plone
Classifier: Framework :: Plone :: 6.0
Classifier: Framework :: Plone :: Core
Classifier: License :: OSI Approved :: GNU General Public License (GPL)
Classifier: Programming Language :: Python
Classifier: Programming Language :: Python :: 3.8
Classifier: Programming Language :: Python :: 3.9
Classifier: Programming Language :: Python :: 3.10
Classifier: Programming Language :: Python :: 3.11
Requires-Python: >=3.8
Requires-Dist: Products.CMFCore
Requires-Dist: setuptools
Requires-Dist: pywin32 ; platform_system == "Windows"
Provides-Extra: test
Requires-Dist: plone.app.contenttypes[test] ; extra == 'test'
Requires-Dist: plone.app.testing ; extra == 'test'
